dkv-0.1.3.1.data/purelib/dkv/__init__.py
dkv-0.1.3.1.data/purelib/dkv/distkv_cli.py
dkv-0.1.3.1.data/purelib/dkv/distkv_server.py
dkv-0.1.3.1.data/purelib/dkv/jars/distkv-cli.jar
dkv-0.1.3.1.data/purelib/dkv/jars/distkv-server.jar
dkv-0.1.3.1.dist-info/METADATA
dkv-0.1.3.1.dist-info/WHEEL
dkv-0.1.3.1.dist-info/entry_points.txt
dkv-0.1.3.1.dist-info/top_level.txt
dkv-0.1.3.1.dist-info/RECORD
