Metadata-Version: 2.1
Name: dkv
Version: 0.1.3.1
Summary: A distributed key-value in-memory store system with table concept.
Home-page: https://github.com/distkv-project/distkv
Author: Qing Wang
Author-email: kingchin1218@gmail.com
License: BSD-3-clause
Platform: UNKNOWN
